odoo8_addon_mrp_analytic-8.0.1.0.0.99.dev13-py2.7-nspkg.pth
odoo8_addon_mrp_analytic-8.0.1.0.0.99.dev13.dist-info/METADATA
odoo8_addon_mrp_analytic-8.0.1.0.0.99.dev13.dist-info/RECORD
odoo8_addon_mrp_analytic-8.0.1.0.0.99.dev13.dist-info/WHEEL
odoo8_addon_mrp_analytic-8.0.1.0.0.99.dev13.dist-info/namespace_packages.txt
odoo8_addon_mrp_analytic-8.0.1.0.0.99.dev13.dist-info/top_level.txt
odoo_addons/mrp_analytic/README.rst
odoo_addons/mrp_analytic/__init__.py
odoo_addons/mrp_analytic/__openerp__.py
odoo_addons/mrp_analytic/i18n/ca.po
odoo_addons/mrp_analytic/i18n/de.po
odoo_addons/mrp_analytic/i18n/el_GR.po
odoo_addons/mrp_analytic/i18n/es.po
odoo_addons/mrp_analytic/i18n/es_MX.po
odoo_addons/mrp_analytic/i18n/fi.po
odoo_addons/mrp_analytic/i18n/fr.po
odoo_addons/mrp_analytic/i18n/hr.po
odoo_addons/mrp_analytic/i18n/mrp_analytic.pot
odoo_addons/mrp_analytic/i18n/pt_BR.po
odoo_addons/mrp_analytic/i18n/sk_SK.po
odoo_addons/mrp_analytic/i18n/sl.po
odoo_addons/mrp_analytic/i18n/tr.po
odoo_addons/mrp_analytic/i18n/zh_CN.po
odoo_addons/mrp_analytic/models/__init__.py
odoo_addons/mrp_analytic/models/analytic_account.py
odoo_addons/mrp_analytic/models/mrp_production.py
odoo_addons/mrp_analytic/static/description/icon.png
odoo_addons/mrp_analytic/static/description/icon.svg
odoo_addons/mrp_analytic/tests/__init__.py
odoo_addons/mrp_analytic/tests/test_mrp_analytic.py
odoo_addons/mrp_analytic/views/analytic_account_view.xml
odoo_addons/mrp_analytic/views/mrp_view.xml
