Metadata-Version: 2.1
Name: odoo8-addon-mrp-analytic
Version: 8.0.1.0.0.99.dev13
Summary: Adds the analytic account to the production order
Home-page: https://github.com/OCA/account-analytic
Author: Eficent, Antiun Ingeniería, Serv. Tecnol. Avanzados - Pedro M. Baeza, Odoo Community Association (OCA)
Author-email: support@odoo-community.org
License: AGPL-3
Platform: UNKNOWN
Classifier: Programming Language :: Python
Classifier: Framework :: Odoo
Classifier: License :: OSI Approved :: GNU Affero General Public License v3
Requires-Python: ~=2.7
Requires-Dist: odoo (<9.0a,>=8.0a)
